mdformat_ado_toc/__init__.py
mdformat_ado_toc/plugin.py
mdformat_ado_toc-0.0.1.dist-info/METADATA
mdformat_ado_toc-0.0.1.dist-info/WHEEL
mdformat_ado_toc-0.0.1.dist-info/entry_points.txt
mdformat_ado_toc-0.0.1.dist-info/licenses/LICENSE
mdformat_ado_toc-0.0.1.dist-info/RECORD
