Metadata-Version: 2.4
Name: mdformat-ado-toc
Version: 0.0.1
Summary: MDFormat plugin that preserves Azure DevOps [[_TOC_]] directive
Project-URL: Homepage, https://github.com/LuisHenri/mdformat-ado-toc
Project-URL: Repository, https://github.com/LuisHenri/mdformat-ado-toc
Project-URL: Issues, https://github.com/LuisHenri/mdformat-ado-toc/issues
Author: Luís Henrique Allebrandt Schünemann
License-Expression: MIT
License-File: LICENSE
Keywords: ado,azure-devops,formatter,markdown,mdformat,toc
Classifier: Development Status :: 3 - Alpha
Classifier: Intended Audience :: Developers
Classifier: Programming Language :: Python :: 3
Classifier: Programming Language :: Python :: 3.10
Classifier: Programming Language :: Python :: 3.11
Classifier: Programming Language :: Python :: 3.12
Classifier: Programming Language :: Python :: 3.13
Classifier: Topic :: Software Development :: Libraries :: Python Modules
Classifier: Topic :: Text Processing :: Markup :: Markdown
Requires-Python: >=3.10
Requires-Dist: markdown-it-py>=3.0.0
Requires-Dist: mdformat>=1.0.0
